cabek_sdk/__init__.py
cabek_sdk-1.0.0.dist-info/licenses/LICENSE
cabek_sdk-1.0.0.dist-info/METADATA
cabek_sdk-1.0.0.dist-info/WHEEL
cabek_sdk-1.0.0.dist-info/top_level.txt
cabek_sdk-1.0.0.dist-info/RECORD
