Metadata-Version: 2.4
Name: cabek-sdk
Version: 1.0.0
Summary: Official Python SDK for C.A.B.E.K. biometric authentication
Home-page: https://github.com/cabek-tech/cabek-python-sdk
Author: C.A.B.E.K. Technologies
Author-email: "C.A.B.E.K. Technologies" <developers@cabek.io>
Maintainer-email: "C.A.B.E.K. Technologies" <developers@cabek.io>
License: MIT
Project-URL: Homepage, https://github.com/cabek-tech/cabek-python-sdk
Project-URL: Documentation, https://docs.cabek.io/sdk/python
Project-URL: Repository, https://github.com/cabek-tech/cabek-python-sdk
Project-URL: Issues, https://github.com/cabek-tech/cabek-python-sdk/issues
Classifier: Development Status :: 4 - Beta
Classifier: Intended Audience :: Developers
Classifier: Topic :: Software Development :: Libraries :: Python Modules
Classifier: Topic :: Security
Classifier: Topic :: Scientific/Engineering :: Medical Science Apps.
Classifier: License :: OSI Approved :: MIT License
Classifier: Programming Language :: Python :: 3
Classifier: Programming Language :: Python :: 3.8
Classifier: Programming Language :: Python :: 3.9
Classifier: Programming Language :: Python :: 3.10
Classifier: Programming Language :: Python :: 3.11
Classifier: Programming Language :: Python :: 3.12
Classifier: Operating System :: OS Independent
Requires-Python: >=3.8
License-File: LICENSE
Requires-Dist: aiohttp>=3.8.0
Requires-Dist: websockets>=10.0
Requires-Dist: numpy>=1.20.0
Provides-Extra: dev
Requires-Dist: pytest>=7.0.0; extra == "dev"
Requires-Dist: pytest-asyncio>=0.21.0; extra == "dev"
Requires-Dist: pytest-cov>=4.0.0; extra == "dev"
Requires-Dist: black>=23.0.0; extra == "dev"
Requires-Dist: flake8>=6.0.0; extra == "dev"
Requires-Dist: mypy>=1.0.0; extra == "dev"
Provides-Extra: ecg
Requires-Dist: scipy>=1.9.0; extra == "ecg"
Requires-Dist: scikit-learn>=1.2.0; extra == "ecg"
Requires-Dist: biosppy>=0.8.0; extra == "ecg"
Dynamic: author
Dynamic: home-page
Dynamic: license-file
Dynamic: requires-python
